cnutils/__init__.py
cnutils/cnumb.py
cnutils/cutils.py
cnutils/fs_lib.py
cnutils-0.1.41.dist-info/LICENSE
cnutils-0.1.41.dist-info/METADATA
cnutils-0.1.41.dist-info/WHEEL
cnutils-0.1.41.dist-info/top_level.txt
cnutils-0.1.41.dist-info/RECORD
